uncatchable_exception.py
uncatchable_exception-0.1.2.dist-info/top_level.txt
uncatchable_exception-0.1.2.dist-info/METADATA
uncatchable_exception-0.1.2.dist-info/DESCRIPTION.rst
uncatchable_exception-0.1.2.dist-info/pydist.json
uncatchable_exception-0.1.2.dist-info/WHEEL
uncatchable_exception-0.1.2.dist-info/RECORD
