Metadata-Version: 2.0
Name: uncatchable-exception
Version: 0.1.2
Summary: An exception class which is not catchable when it was raised.
Home-page: https://github.com/bh/uncatchable-exception
Author: Benjamin Hedrich
Author-email: benjamin.hedrich@pagenotfound.de
License: BSD
Platform: UNKNOWN
Classifier: Intended Audience :: Developers
Classifier: License :: OSI Approved :: BSD License
Classifier: Programming Language :: Python
Classifier: Programming Language :: Python :: 2
Classifier: Programming Language :: Python :: 2.7
Classifier: Programming Language :: Python :: 3
Classifier: Programming Language :: Python :: 3.3
Classifier: Programming Language :: Python :: 3.4
Classifier: Programming Language :: Python :: Implementation :: CPython
Classifier: Programming Language :: Python :: Implementation :: PyPy
Classifier: Topic :: Software Development :: Libraries
Classifier: Topic :: Utilities
